{
    "data": [
        {
            "locale": "zh-Hans",
            "data": {
                "label": "GPUImage-Plus",
                "dev_team": "wysaid",
                "rule_contributors": [
                    "crrashh1542"
                ],
                "description": "一个可用于图片、实时摄像和视频的 C++ & Java 的滤镜处理库。",
                "source_link": "https://github.com/wysaid/android-gpuimage-plus"
            }
        },
        {
            "locale": "en",
            "data": {
                "label": "GPUImage-Plus",
                "dev_team": "wysaid",
                "rule_contributors": [
                    "crrashh1542"
                ],
                "description": "A C++ & Java filter processing library for images, real-time camera feeds, and video.",
                "source_link": "https://github.com/wysaid/android-gpuimage-plus"
            }
        }
    ],
    "uuid": "D4449A0B-FB85-4137-8D35-C3E8B04C52F6"
}